LICENSE
MANIFEST.in
README.md
TUTORIAL.md
pyproject.toml
setup.py
./vendor/src/termgl.c
termgl/__init__.pyi
termgl/ctermgl.pxd
termgl/ctermglutil.pxd
termgl/py.typed
termgl/termgl.pyx
termgl.egg-info/PKG-INFO
termgl.egg-info/SOURCES.txt
termgl.egg-info/dependency_links.txt
termgl.egg-info/requires.txt
termgl.egg-info/top_level.txt
vendor/LICENSE.txt
vendor/lib/termgl.h
vendor/src/termgl.c