Metadata-Version: 2.1
Name: termgl
Version: 0.2.1
Summary: Terminal-based 2D & 3D graphics library.
Author: Wojciech Graj
License: MIT License
Project-URL: Repository, https://github.com/wojciech-graj/pyTermGL
Keywords: graphics,terminal,render,rendering,text,ascii
Classifier: Development Status :: 4 - Beta
Classifier: Intended Audience :: Developers
Classifier: Environment :: Console
Classifier: Topic :: Multimedia :: Graphics
Classifier: Topic :: Multimedia :: Graphics :: 3D Rendering
Classifier: Topic :: Terminals
Classifier: License :: OSI Approved :: MIT License
Classifier: Programming Language :: Python :: 3.11
Classifier: Programming Language :: Python :: 3.12
Classifier: Programming Language :: Python :: 3.13
Classifier: Programming Language :: Cython
Requires-Python: >=3.11
License-File: LICENSE
Requires-Dist: numpy>=1.25
Provides-Extra: dev
Requires-Dist: pdoc; extra == "dev"
Requires-Dist: pylsp-mypy; extra == "dev"
Requires-Dist: pylsp-rope; extra == "dev"
Requires-Dist: pytest; extra == "dev"
Requires-Dist: python-lsp-isort; extra == "dev"
Requires-Dist: python-lsp-server[all]; extra == "dev"
